bfrvc/__init__.py
bfrvc/core.py
bfrvc-0.5.2.dist-info/licenses/LICENSE
bfrvc-0.5.2.dist-info/METADATA
bfrvc-0.5.2.dist-info/WHEEL
bfrvc-0.5.2.dist-info/entry_points.txt
bfrvc-0.5.2.dist-info/top_level.txt
bfrvc-0.5.2.dist-info/RECORD
